stspacepen/__init__.py
stspacepen-0.0.1.dist-info/LICENSE.txt
stspacepen-0.0.1.dist-info/METADATA
stspacepen-0.0.1.dist-info/WHEEL
stspacepen-0.0.1.dist-info/top_level.txt
stspacepen-0.0.1.dist-info/RECORD
