Metadata-Version: 2.1
Name: stspacepen
Version: 0.0.1
Summary: A Python Pen
Home-page: UNKNOWN
Author: ST
Author-email: amazingfalcon1@gmail.com
License: MIT
Keywords: pen
Platform: UNKNOWN
Classifier: Development Status :: 5 - Production/Stable
Classifier: Intended Audience :: Education
Classifier: Operating System :: Microsoft :: Windows :: Windows 10
Classifier: License :: OSI Approved :: MIT License
Classifier: Programming Language :: Python :: 3
License-File: LICENSE.txt
